{
  "code": 200,
  "message": "ok",
  "total": 7,
  "userlist": [
    {
      "id": "526547658",
      "no": "234325432",
      "name": "摄像头111",
      "map": "",
      "latitude" : "",
      "longitude" : ""
    },
    {
      "id": "526547658",
      "no": "234325432",
      "name": "摄像头111",
      "map": "工地所在地图-2F",
      "latitude" : "43.270112",
      "longitude" : "1.656832"
    },
    {
      "id": "526547658",
      "no": "234325432",
      "name": "摄像头111",
      "map": "工地所在地图-2F",
      "latitude" : "43.907572",
      "longitude" : "-70.221725"
    },
    {
      "id": "526547658",
      "no": "234325432",
      "name": "摄像头111",
      "map": "工地所在地图-2F",
      "latitude" : "43.907572",
      "longitude" : "-70.221725"
    },
    {
      "id": "526547658",
      "no": "234325432",
      "name": "摄像头111",
      "map": "",
      "latitude" : "",
      "longitude" : ""
    },
    {
      "id": "526547658",
      "no": "234325432",
      "name": "摄像头111",
      "map": "工地所在地图-2F",
      "latitude" : "43.907572",
      "longitude" : "-70.221725"
    },
    {
      "id": "526547658",
      "no": "234325432",
      "name": "摄像头111",
      "map": "",
      "latitude" : "",
      "longitude" : ""
    }
  ]
}